<annotation>
	<folder>images</folder>
	<filename>3.jpg</filename>
	<path>C:/Users/hp/Documents/images/3.jpg</path>
	<source>
		<database>Unknown</database>
	</source>
	<size>
		<width>2560</width>
		<height>1708</height>
		<depth>3</depth>
	</size>
	<segmented>0</segmented>
	<object>
		<name>obama</name>
		<pose>Unspecified</pose>
		<truncated>0</truncated>
		<difficult>0</difficult>
		<bndbox>
			<xmin>965</xmin>
			<ymin>179</ymin>
			<xmax>1594</xmax>
			<ymax>811</ymax>
		</bndbox>
	</object>
</annotation>
